faceattend/__init__.py
faceattend/attendance.py
faceattend/create_database.py
faceattend/detect.py
faceattend/face.py
faceattend-0.0.2.dist-info/METADATA
faceattend-0.0.2.dist-info/WHEEL
faceattend-0.0.2.dist-info/top_level.txt
faceattend-0.0.2.dist-info/RECORD
