Metadata-Version: 2.1
Name: faceattend
Version: 0.0.2
Summary: An attendance system using face recognition
Home-page: https://github.com/AkashMondal1998/FaceAttend
Author: Akash Mondal
Author-email: mondalakash63@gmail.com
License: MIT license
Platform: UNKNOWN
Classifier: Development Status :: 2 - Pre-Alpha
Classifier: Intended Audience :: Science/Research
Classifier: License :: OSI Approved :: MIT License
Classifier: Operating System :: POSIX :: Linux
Classifier: Programming Language :: Python :: 2
Classifier: Programming Language :: Python :: 2.7
Classifier: Programming Language :: Python :: 3
Classifier: Programming Language :: Python :: 3.4
Classifier: Programming Language :: Python :: 3.5
Requires-Dist: face-recognition
Requires-Dist: gTTS
Requires-Dist: pygame
Requires-Dist: opencv-python
